erc6492_signature_verifier/__init__.py
erc6492_signature_verifier/binary_data.py
erc6492_signature_verifier/concat.py
erc6492_signature_verifier/contracts/UniversalSigValidator.sol
erc6492_signature_verifier/contracts/ValidateSigOffchain.sol
erc6492_signature_verifier/hash_msg.py
erc6492_signature_verifier/signature_verifier.py
erc6492_signature_verifier-0.2.1.dist-info/LICENSE
erc6492_signature_verifier-0.2.1.dist-info/METADATA
erc6492_signature_verifier-0.2.1.dist-info/WHEEL
erc6492_signature_verifier-0.2.1.dist-info/RECORD
