Metadata-Version: 2.1
Name: erc6492_signature_verifier
Version: 0.2.1
Summary: A Python library for verifying Ethereum signatures in compliance with EIP-6492, supporting both smart contracts and externally owned accounts (EOA).
License: MIT
Author: Sajad
Author-email: SajadSolidity@gmail.com
Requires-Python: >=3.9,<4.0
Classifier: License :: OSI Approved :: MIT License
Classifier: Operating System :: OS Independent
Classifier: Programming Language :: Python :: 3
Classifier: Programming Language :: Python :: 3.9
Classifier: Programming Language :: Python :: 3.10
Classifier: Programming Language :: Python :: 3.11
Classifier: Programming Language :: Python :: 3.12
Requires-Dist: safe-pysha3 (>=1.0.4,<2.0.0)
Requires-Dist: web3 (>=6.20.1,<7.0.0)
